src/__init__.py
src/module1.py
src/module2.py
src/module3.py
src/module4.py
pasqui-0.1.0.dist-info/LICENSE
pasqui-0.1.0.dist-info/METADATA
pasqui-0.1.0.dist-info/WHEEL
pasqui-0.1.0.dist-info/top_level.txt
pasqui-0.1.0.dist-info/RECORD
