Metadata-Version: 2.1
Name: pasqui
Version: 0.1.0
Summary: This python library is useful to perform serveral functions needed to structure unstructured text,
Home-page: https://github.com/NcabreraM/pasqui
Author: Natalia Cabrera-Morales
Author-email: natalia.cabrera.m@mail.pucv.cl
License: MIT
License-File: LICENSE
Requires-Dist: pdfplumber
Requires-Dist: python-docx
Requires-Dist: openai
Requires-Dist: tiktoken
Requires-Dist: pandas
Requires-Dist: scipy
Requires-Dist: langchain
Requires-Dist: kor
Requires-Dist: requests
Requires-Dist: markdownify
Requires-Dist: scikit-learn
Requires-Dist: langchain-community
Requires-Dist: langchain-openai
